renta/__init__.py
renta/ai.py
renta/analyzer.py
renta/cli.py
renta/config.py
renta/exceptions.py
renta/export.py
renta/ingestion.py
renta/interfaces.py
renta/security.py
renta/spatial.py
renta/data/default_config.yaml
renta/data/legal_notice.md
renta/prompts/__init__.py
renta/prompts/investment_summary.yaml
renta/schemas/__init__.py
renta/schemas/config_schema.json
renta/utils/__init__.py
renta/utils/retry.py
renta-0.1.2.dist-info/licenses/LICENSE
renta-0.1.2.dist-info/METADATA
renta-0.1.2.dist-info/WHEEL
renta-0.1.2.dist-info/entry_points.txt
renta-0.1.2.dist-info/top_level.txt
renta-0.1.2.dist-info/RECORD
