Metadata-Version: 2.4
Name: renta
Version: 0.1.2
Summary: Real Estate Network and Trend Analyzer - A Python library for real estate investment analysis in Buenos Aires
Author-email: RENTA Development Team <contact@renta.dev>
Maintainer-email: RENTA Development Team <contact@renta.dev>
License-Expression: MIT
Project-URL: Homepage, https://github.com/machinelearnear/RENTA
Project-URL: Documentation, https://github.com/machinelearnear/RENTA#readme
Project-URL: Repository, https://github.com/machinelearnear/RENTA
Project-URL: Bug Tracker, https://github.com/machinelearnear/RENTA/issues
Project-URL: Changelog, https://github.com/machinelearnear/RENTA/blob/main/CHANGELOG.md
Keywords: real-estate,airbnb,investment-analysis,buenos-aires,property-analysis,rental-market,ai-analysis
Classifier: Development Status :: 3 - Alpha
Classifier: Intended Audience :: Developers
Classifier: Intended Audience :: Financial and Insurance Industry
Classifier: Operating System :: OS Independent
Classifier: Programming Language :: Python :: 3
Classifier: Programming Language :: Python :: 3.10
Classifier: Programming Language :: Python :: 3.11
Classifier: Programming Language :: Python :: 3.12
Classifier: Topic :: Office/Business :: Financial :: Investment
Classifier: Topic :: Scientific/Engineering :: Information Analysis
Classifier: Topic :: Software Development :: Libraries :: Python Modules
Requires-Python: >=3.10
License-File: LICENSE
Requires-Dist: pandas==2.2.3
Requires-Dist: numpy==1.26.4
Requires-Dist: requests==2.31.0
Requires-Dist: beautifulsoup4==4.12.3
Requires-Dist: lxml==5.3.0
Requires-Dist: scikit-learn==1.5.2
Requires-Dist: pyyaml==6.0.2
Requires-Dist: jsonschema==4.23.0
Requires-Dist: boto3==1.35.70
Requires-Dist: botocore==1.35.70
Requires-Dist: jinja2==3.1.4
Requires-Dist: structlog==24.4.0
Requires-Dist: tqdm==4.67.1
Provides-Extra: dev
Requires-Dist: pytest>=7.0.0; extra == "dev"
Requires-Dist: pytest-cov>=4.0.0; extra == "dev"
Requires-Dist: pytest-mock>=3.10.0; extra == "dev"
Requires-Dist: pytest-asyncio>=0.21.0; extra == "dev"
Requires-Dist: black>=23.0.0; extra == "dev"
Requires-Dist: isort>=5.12.0; extra == "dev"
Requires-Dist: flake8>=6.0.0; extra == "dev"
Requires-Dist: mypy>=1.0.0; extra == "dev"
Requires-Dist: mkdocs>=1.4.0; extra == "dev"
Requires-Dist: mkdocs-material>=9.0.0; extra == "dev"
Requires-Dist: mkdocstrings[python]>=0.20.0; extra == "dev"
Requires-Dist: build>=0.10.0; extra == "dev"
Requires-Dist: twine>=4.0.0; extra == "dev"
Provides-Extra: scraping
Requires-Dist: playwright>=1.40.0; extra == "scraping"
Requires-Dist: cloudscraper>=1.2.71; extra == "scraping"
Requires-Dist: python-dotenv>=1.0.0; extra == "scraping"
Provides-Extra: security
Requires-Dist: pip-audit>=2.0.0; extra == "security"
Requires-Dist: safety>=3.0.0; extra == "security"
Requires-Dist: bandit>=1.7.0; extra == "security"
Provides-Extra: test
Requires-Dist: pytest>=7.0.0; extra == "test"
Requires-Dist: pytest-cov>=4.0.0; extra == "test"
Requires-Dist: pytest-mock>=3.10.0; extra == "test"
Requires-Dist: pytest-asyncio>=0.21.0; extra == "test"
Provides-Extra: docs
Requires-Dist: mkdocs>=1.4.0; extra == "docs"
Requires-Dist: mkdocs-material>=9.0.0; extra == "docs"
Requires-Dist: mkdocstrings[python]>=0.20.0; extra == "docs"
Dynamic: license-file
